{"1953260":{"success":true,"data":{"type":"demo","name":"小虎传：大菠萝深渊 试玩版","steam_appid":1953260,"required_age":0,"is_free":true,"detailed_description":"你穿越到了异世界——大菠萝深渊，这里危机四伏、妖怪横行，你为寻找回家的路踏上了征程。<br>你将在深渊中到处探险：收集食物以充饥、采摘药草以疗伤，击杀妖怪以升级，带回丰厚的战利品，打造珍稀的装备。<br>随着你的实力逐渐强大，你将通过一次次战斗的考验，前往深渊的底层，发现更多的地域风貌、妖怪、秘密，获得更稀有的装备、技能、宝具，结识更多形形色色的伙伴，助你突破十八层大深渊。<br><br><br><strong><h2 class=\"bb_tag\">游戏特色<\/h2><\/strong><br><br><strong>随机的世界<\/strong>：随机生成各种地形、环境、遭遇的十八层大深渊，你将面临完全未知的挑战以及令人兴奋不已的机遇！<br><br><strong>多样的风貌<\/strong>：盛产果实药草的森林、贫瘠却多矿石的岩地、有鱼群却潮湿难行的水域，还有充满神秘、人迹罕至的危险地带诸如沙漠、沼泽、雪地…<br><br><strong>自由的策略<\/strong>：你要妥善安排你的时间，是在城里打工还是外出探险？是去采果充饥还是去挖矿赚钱？面对随机的世界，变化的资源，你将采取怎样的策略？<br><br><strong>大量的装备<\/strong>：作为一款点点点、刷刷刷的游戏，各种类型、品质、随机词条加成属性的装备当然是必不可少啦~！<br><br><strong>随缘的伙伴<\/strong>：你会在旅途中随缘结识到各种伙伴，他们各有不同的属性成长和技能。你将如何培养搭配、培养，打造出一支强力而默契的队伍？<br><br><strong>简明的主线<\/strong>：将随机丰富的游戏过程和简单明了的剧情结合，令游玩体验变得更有目标和意义。","about_the_game":"你穿越到了异世界——大菠萝深渊，这里危机四伏、妖怪横行，你为寻找回家的路踏上了征程。<br>你将在深渊中到处探险：收集食物以充饥、采摘药草以疗伤，击杀妖怪以升级，带回丰厚的战利品，打造珍稀的装备。<br>随着你的实力逐渐强大，你将通过一次次战斗的考验，前往深渊的底层，发现更多的地域风貌、妖怪、秘密，获得更稀有的装备、技能、宝具，结识更多形形色色的伙伴，助你突破十八层大深渊。<br><br><br><strong><h2 class=\"bb_tag\">游戏特色<\/h2><\/strong><br><br><strong>随机的世界<\/strong>：随机生成各种地形、环境、遭遇的十八层大深渊，你将面临完全未知的挑战以及令人兴奋不已的机遇！<br><br><strong>多样的风貌<\/strong>：盛产果实药草的森林、贫瘠却多矿石的岩地、有鱼群却潮湿难行的水域，还有充满神秘、人迹罕至的危险地带诸如沙漠、沼泽、雪地…<br><br><strong>自由的策略<\/strong>：你要妥善安排你的时间，是在城里打工还是外出探险？是去采果充饥还是去挖矿赚钱？面对随机的世界，变化的资源，你将采取怎样的策略？<br><br><strong>大量的装备<\/strong>：作为一款点点点、刷刷刷的游戏，各种类型、品质、随机词条加成属性的装备当然是必不可少啦~！<br><br><strong>随缘的伙伴<\/strong>：你会在旅途中随缘结识到各种伙伴，他们各有不同的属性成长和技能。你将如何培养搭配、培养，打造出一支强力而默契的队伍？<br><br><strong>简明的主线<\/strong>：将随机丰富的游戏过程和简单明了的剧情结合，令游玩体验变得更有目标和意义。","short_description":"随机生成十八层深渊，多种地型环境风貌和遭遇。你将在深渊中到处探险、收集食物和药草，击杀妖怪获得战利品，打造珍稀的装备，逐步提升自身的实力！","fullgame":{"appid":"1945230","name":"小虎传：大菠萝深渊"},"supported_languages":"Simplified Chinese","header_image":"https:\/\/cdn.akamai.steamstatic.com\/steam\/apps\/1953260\/header.jpg?t=1651155107","website":"","pc_requirements":{"minimum":"<strong>Minimum:<\/strong><br><ul class=\"bb_ul\"><li><strong>OS:<\/strong> Windows 7, Windows 10, x64 system<br><\/li><li><strong>Processor:<\/strong> Intel Core2 Duo E4300 (2 * 1800) \/ AMD Athlon Dual Core 4450e (2 * 2300) or equivalent<br><\/li><li><strong>Memory:<\/strong> 4 GB RAM<br><\/li><li><strong>Graphics:<\/strong> GeForce 8800 GTX (768 MB) \/ Intel HD 4600 \/ Radeon HD 3850 (512 MB)<br><\/li><li><strong>DirectX:<\/strong> Version 10<br><\/li><li><strong>Storage:<\/strong> 800 MB available space<\/li><\/ul>"},"mac_requirements":[],"linux_requirements":[],"developers":["波波工作室"],"publishers":["波波工作室"],"packages":[704552],"package_groups":[],"platforms":{"windows":true,"mac":false,"linux":false},"categories":[{"id":2,"description":"Single-player"},{"id":10,"description":"Game demo"}],"genres":[{"id":"25","description":"Adventure"},{"id":"23","description":"Indie"},{"id":"3","description":"RPG"},{"id":"2","description":"Strategy"},{"id":"70","description":"Early Access"}],"screenshots":[{"id":0,"path_thumbnail":"https:\/\/cdn.akamai.steamstatic.com\/steam\/apps\/1953260\/ss_3453a9311101a1218c0c9b372879aec820dbadd0.600x338.jpg?t=1651155107","path_full":"https:\/\/cdn.akamai.steamstatic.com\/steam\/apps\/1953260\/ss_3453a9311101a1218c0c9b372879aec820dbadd0.1920x1080.jpg?t=1651155107"},{"id":1,"path_thumbnail":"https:\/\/cdn.akamai.steamstatic.com\/steam\/apps\/1953260\/ss_dbe962d14fa663efa2f27e76041b3c4cf949644f.600x338.jpg?t=1651155107","path_full":"https:\/\/cdn.akamai.steamstatic.com\/steam\/apps\/1953260\/ss_dbe962d14fa663efa2f27e76041b3c4cf949644f.1920x1080.jpg?t=1651155107"},{"id":2,"path_thumbnail":"https:\/\/cdn.akamai.steamstatic.com\/steam\/apps\/1953260\/ss_a4a22c83bccd2d0bf504e4784fd8f32c25ea8ccc.600x338.jpg?t=1651155107","path_full":"https:\/\/cdn.akamai.steamstatic.com\/steam\/apps\/1953260\/ss_a4a22c83bccd2d0bf504e4784fd8f32c25ea8ccc.1920x1080.jpg?t=1651155107"},{"id":3,"path_thumbnail":"https:\/\/cdn.akamai.steamstatic.com\/steam\/apps\/1953260\/ss_e4ef61511cf182ec9a23d090247d162f48f30143.600x338.jpg?t=1651155107","path_full":"https:\/\/cdn.akamai.steamstatic.com\/steam\/apps\/1953260\/ss_e4ef61511cf182ec9a23d090247d162f48f30143.1920x1080.jpg?t=1651155107"},{"id":4,"path_thumbnail":"https:\/\/cdn.akamai.steamstatic.com\/steam\/apps\/1953260\/ss_43cd7445211975f75f506cb39c24de4b01bf556c.600x338.jpg?t=1651155107","path_full":"https:\/\/cdn.akamai.steamstatic.com\/steam\/apps\/1953260\/ss_43cd7445211975f75f506cb39c24de4b01bf556c.1920x1080.jpg?t=1651155107"},{"id":5,"path_thumbnail":"https:\/\/cdn.akamai.steamstatic.com\/steam\/apps\/1953260\/ss_992c5e04f864c73a7207c1303b006cefd6844775.600x338.jpg?t=1651155107","path_full":"https:\/\/cdn.akamai.steamstatic.com\/steam\/apps\/1953260\/ss_992c5e04f864c73a7207c1303b006cefd6844775.1920x1080.jpg?t=1651155107"},{"id":6,"path_thumbnail":"https:\/\/cdn.akamai.steamstatic.com\/steam\/apps\/1953260\/ss_fac861a212ce70e1d011d5c5858dede5fa946ec2.600x338.jpg?t=1651155107","path_full":"https:\/\/cdn.akamai.steamstatic.com\/steam\/apps\/1953260\/ss_fac861a212ce70e1d011d5c5858dede5fa946ec2.1920x1080.jpg?t=1651155107"},{"id":7,"path_thumbnail":"https:\/\/cdn.akamai.steamstatic.com\/steam\/apps\/1953260\/ss_f92b097f1e69d0ee3b811abb7ac413c06e4ceafb.600x338.jpg?t=1651155107","path_full":"https:\/\/cdn.akamai.steamstatic.com\/steam\/apps\/1953260\/ss_f92b097f1e69d0ee3b811abb7ac413c06e4ceafb.1920x1080.jpg?t=1651155107"},{"id":8,"path_thumbnail":"https:\/\/cdn.akamai.steamstatic.com\/steam\/apps\/1953260\/ss_50c452bd8d7c82b0a212817baa00726c56fb1a11.600x338.jpg?t=1651155107","path_full":"https:\/\/cdn.akamai.steamstatic.com\/steam\/apps\/1953260\/ss_50c452bd8d7c82b0a212817baa00726c56fb1a11.1920x1080.jpg?t=1651155107"}],"movies":[{"id":256881146,"name":"介绍动画","thumbnail":"https:\/\/cdn.akamai.steamstatic.com\/steam\/apps\/256881146\/movie.293x165.jpg?t=1649321050","webm":{"480":"http:\/\/cdn.akamai.steamstatic.com\/steam\/apps\/256881146\/movie480_vp9.webm?t=1649321050","max":"http:\/\/cdn.akamai.steamstatic.com\/steam\/apps\/256881146\/movie_max_vp9.webm?t=1649321050"},"mp4":{"480":"http:\/\/cdn.akamai.steamstatic.com\/steam\/apps\/256881146\/movie480.mp4?t=1649321050","max":"http:\/\/cdn.akamai.steamstatic.com\/steam\/apps\/256881146\/movie_max.mp4?t=1649321050"},"highlight":true}],"release_date":{"coming_soon":false,"date":"6 Apr, 2022"},"support_info":{"url":"https:\/\/space.bilibili.com\/211508805","email":"6143471@qq.com"},"background":"https:\/\/cdn.akamai.steamstatic.com\/steam\/apps\/1953260\/page_bg_generated_v6b.jpg?t=1651155107","background_raw":"https:\/\/cdn.akamai.steamstatic.com\/steam\/apps\/1953260\/page_bg_generated.jpg?t=1651155107","content_descriptors":{"ids":[],"notes":null}}}}