{"1922920":{"success":true,"data":{"type":"music","name":"Abermore - Original Soundtrack","steam_appid":1922920,"required_age":0,"is_free":false,"detailed_description":"The soundtrack for Abermore include a combination of unhinged organs, synths, disformed instruments and driving percussion. <br \/>\r\nA product of 5 years of experimentation and strife.","about_the_game":"The soundtrack for Abermore include a combination of unhinged organs, synths, disformed instruments and driving percussion. <br \/>\r\nA product of 5 years of experimentation and strife.","short_description":"Estranged instrumentation for the equally estranged city of Abermore. Abermore: A First-Person stealth game where you abscond with ill gotten goods in preparation for the big job: Ruin Theobald's Feast.","header_image":"https:\/\/cdn.akamai.steamstatic.com\/steam\/apps\/1922920\/header.jpg?t=1648688203","website":null,"pc_requirements":{"minimum":"<strong>Minimum:<\/strong><br><ul class=\"bb_ul\"><li><strong>Storage:<\/strong> 224 MB available space<br><\/li><li><strong>Storage (high-quality audio):<\/strong> Additional 884 MB available space<\/li><\/ul>"},"mac_requirements":[],"linux_requirements":[],"developers":["Tim Rurkowski"],"publishers":["Tim Rurkowski"],"price_overview":{"currency":"UAH","initial":11900,"final":11900,"discount_percent":0,"initial_formatted":"","final_formatted":"119₴"},"packages":[692736],"package_groups":[{"name":"default","title":"Buy Abermore - Original Soundtrack","description":"","selection_text":"Select a purchase option","save_text":"","display_type":0,"is_recurring_subscription":"false","subs":[{"packageid":692736,"percent_savings_text":" ","percent_savings":0,"option_text":"Abermore - Original Soundtrack - 119₴","option_description":"","can_get_free_license":"0","is_free_license":false,"price_in_cents_with_discount":11900}]}],"platforms":{"windows":true,"mac":true,"linux":true},"categories":[{"id":50,"description":"Additional High-Quality Audio"}],"screenshots":[{"id":0,"path_thumbnail":"https:\/\/cdn.akamai.steamstatic.com\/steam\/apps\/1922920\/ss_536f49f10e3561fc8431ac7581029efd68223e15.600x338.jpg?t=1648688203","path_full":"https:\/\/cdn.akamai.steamstatic.com\/steam\/apps\/1922920\/ss_536f49f10e3561fc8431ac7581029efd68223e15.1920x1080.jpg?t=1648688203"},{"id":1,"path_thumbnail":"https:\/\/cdn.akamai.steamstatic.com\/steam\/apps\/1922920\/ss_1af1d94c8771361db04ce6c8c293f1e38fc5c806.600x338.jpg?t=1648688203","path_full":"https:\/\/cdn.akamai.steamstatic.com\/steam\/apps\/1922920\/ss_1af1d94c8771361db04ce6c8c293f1e38fc5c806.1920x1080.jpg?t=1648688203"},{"id":2,"path_thumbnail":"https:\/\/cdn.akamai.steamstatic.com\/steam\/apps\/1922920\/ss_5c57ce375bbe75b604d77b6c83e108e400118f2b.600x338.jpg?t=1648688203","path_full":"https:\/\/cdn.akamai.steamstatic.com\/steam\/apps\/1922920\/ss_5c57ce375bbe75b604d77b6c83e108e400118f2b.1920x1080.jpg?t=1648688203"},{"id":3,"path_thumbnail":"https:\/\/cdn.akamai.steamstatic.com\/steam\/apps\/1922920\/ss_5b73d33ea5f8fc7822c1727d61715a69794dfe32.600x338.jpg?t=1648688203","path_full":"https:\/\/cdn.akamai.steamstatic.com\/steam\/apps\/1922920\/ss_5b73d33ea5f8fc7822c1727d61715a69794dfe32.1920x1080.jpg?t=1648688203"},{"id":4,"path_thumbnail":"https:\/\/cdn.akamai.steamstatic.com\/steam\/apps\/1922920\/ss_57061effcd04579baa88481c3f7a8c033d900673.600x338.jpg?t=1648688203","path_full":"https:\/\/cdn.akamai.steamstatic.com\/steam\/apps\/1922920\/ss_57061effcd04579baa88481c3f7a8c033d900673.1920x1080.jpg?t=1648688203"},{"id":5,"path_thumbnail":"https:\/\/cdn.akamai.steamstatic.com\/steam\/apps\/1922920\/ss_a1be2e17d7b4aa7e5707bb816cc65560cbe5e5f8.600x338.jpg?t=1648688203","path_full":"https:\/\/cdn.akamai.steamstatic.com\/steam\/apps\/1922920\/ss_a1be2e17d7b4aa7e5707bb816cc65560cbe5e5f8.1920x1080.jpg?t=1648688203"},{"id":6,"path_thumbnail":"https:\/\/cdn.akamai.steamstatic.com\/steam\/apps\/1922920\/ss_e20c6a2cbb39641cfd453667ff75bbf0b61db058.600x338.jpg?t=1648688203","path_full":"https:\/\/cdn.akamai.steamstatic.com\/steam\/apps\/1922920\/ss_e20c6a2cbb39641cfd453667ff75bbf0b61db058.1920x1080.jpg?t=1648688203"},{"id":7,"path_thumbnail":"https:\/\/cdn.akamai.steamstatic.com\/steam\/apps\/1922920\/ss_b0cb840292eadd14d39133ffeb00eb2a172942d8.600x338.jpg?t=1648688203","path_full":"https:\/\/cdn.akamai.steamstatic.com\/steam\/apps\/1922920\/ss_b0cb840292eadd14d39133ffeb00eb2a172942d8.1920x1080.jpg?t=1648688203"},{"id":8,"path_thumbnail":"https:\/\/cdn.akamai.steamstatic.com\/steam\/apps\/1922920\/ss_27fc00a738e8ca189025bffe1750ee9c218b1bb0.600x338.jpg?t=1648688203","path_full":"https:\/\/cdn.akamai.steamstatic.com\/steam\/apps\/1922920\/ss_27fc00a738e8ca189025bffe1750ee9c218b1bb0.1920x1080.jpg?t=1648688203"}],"movies":[{"id":256880223,"name":"Abermore Original Soundtrack - Self Introduced and Freshly Unhanged","thumbnail":"https:\/\/cdn.akamai.steamstatic.com\/steam\/apps\/256880223\/movie.293x165.jpg?t=1648688202","webm":{"480":"http:\/\/cdn.akamai.steamstatic.com\/steam\/apps\/256880223\/movie480_vp9.webm?t=1648688202","max":"http:\/\/cdn.akamai.steamstatic.com\/steam\/apps\/256880223\/movie_max_vp9.webm?t=1648688202"},"mp4":{"480":"http:\/\/cdn.akamai.steamstatic.com\/steam\/apps\/256880223\/movie480.mp4?t=1648688202","max":"http:\/\/cdn.akamai.steamstatic.com\/steam\/apps\/256880223\/movie_max.mp4?t=1648688202"},"highlight":true},{"id":256878122,"name":"Abermore Original Soundtrack Teaser 2","thumbnail":"https:\/\/cdn.akamai.steamstatic.com\/steam\/apps\/256878122\/movie.293x165.jpg?t=1647445025","webm":{"480":"http:\/\/cdn.akamai.steamstatic.com\/steam\/apps\/256878122\/movie480_vp9.webm?t=1647445025","max":"http:\/\/cdn.akamai.steamstatic.com\/steam\/apps\/256878122\/movie_max_vp9.webm?t=1647445025"},"mp4":{"480":"http:\/\/cdn.akamai.steamstatic.com\/steam\/apps\/256878122\/movie480.mp4?t=1647445025","max":"http:\/\/cdn.akamai.steamstatic.com\/steam\/apps\/256878122\/movie_max.mp4?t=1647445025"},"highlight":true},{"id":256877974,"name":"Abermore Original Soundtrack Teaser","thumbnail":"https:\/\/cdn.akamai.steamstatic.com\/steam\/apps\/256877974\/movie.293x165.jpg?t=1647389502","webm":{"480":"http:\/\/cdn.akamai.steamstatic.com\/steam\/apps\/256877974\/movie480_vp9.webm?t=1647389502","max":"http:\/\/cdn.akamai.steamstatic.com\/steam\/apps\/256877974\/movie_max_vp9.webm?t=1647389502"},"mp4":{"480":"http:\/\/cdn.akamai.steamstatic.com\/steam\/apps\/256877974\/movie480.mp4?t=1647389502","max":"http:\/\/cdn.akamai.steamstatic.com\/steam\/apps\/256877974\/movie_max.mp4?t=1647389502"},"highlight":true}],"release_date":{"coming_soon":false,"date":"29 Mar, 2022"},"support_info":{"url":"","email":"trurkowski@fourcircleinteractive.co.uk"},"background":"https:\/\/cdn.akamai.steamstatic.com\/steam\/apps\/1922920\/page_bg_generated_v6b.jpg?t=1648688203","background_raw":"https:\/\/cdn.akamai.steamstatic.com\/steam\/apps\/1922920\/page_bg_generated.jpg?t=1648688203","content_descriptors":{"ids":[],"notes":null}}}}