{"1760250":{"success":true,"data":{"type":"game","name":"Madden NFL 23","steam_appid":1760250,"required_age":0,"is_free":false,"controller_support":"full","detailed_description":"<h1>Madden NFL 23 All Madden Edition<\/h1><p>Pre-order All Madden Edition and receive:<br><ul class=\"bb_ul\"><li>3-day early access<br><\/li><li>4,600 Madden Points<br><\/li><li>Exclusive Early Access Challenges<br><\/li><li>Choice of  2 Elite Players (1 offensive &amp; 1 defensive)<br><\/li><li>All Madden Gear<br><\/li><li>Madden Strategy Item<\/li><\/ul>Play your way into the history books in Madden NFL 23.<br><br>Control your impact with every decision in all-new ways. Call the shots in Franchise with free agency and trade logic updates. Play your way into the history books in Face of the Franchise: The League, and assemble the most powerful roster in all of Madden Ultimate Team™.<br><br><strong>Face of the Franchise: The League<\/strong><br>The League drops you into your fifth NFL season at a skill position of your choice (QB, WR, RB, CB, MLB), and you’re seeking a fresh start with a new team. Negotiate a 1-year “prove-it” contract with one of 32 NFL teams, and show out with great on-field performance to earn rewards and level up. The addition of New Drive Goals and Drive Summaries allows you to tweak your experience throughout a game and get feedback and rewards based on how well you play. Get performance boosts from weekly activities and training between games while Madden Ratings Adjustor Chad Johnson guides your career development by providing ratings updates as you strive for the highest level of prestige on your Road to 99. Will your NFL career rank among the all-time greats? It’s up to you.<br><br><strong>Franchise<\/strong><br>Plan and strategize like an NFL head coach with refined scouting, staff management, and weekly strategy features to take your Franchise to the top. New athlete motivations like team location and salary demands factor into contract negotiations and add to the drama of NFL free agency within Franchise. Updated Trade Logic AI represents the value of star players more accurately for fair and more realistic offers.<br><br><strong>Madden Ultimate Team<\/strong><br>Develop your dream fantasy roster of current NFL superstars, Hall of Fame legends, and more. Always have something to play for with the first-ever Field Pass challenge and reward tracker in Madden Ultimate Team. Play to earn MUT Champions entry tokens, and choose to compete at your convenience. Simplified Set building lets you navigate your content binder more effectively so you can focus on improving your Ultimate Team roster all season.<br><br>This game includes optional in-game purchases of virtual currency that can be used to acquire virtual in-game items, including a random selection of virtual in-game items.<\/p><br><h1>Madden NFL 23<\/h1><p>Pre-order Madden NFL 23 and receive:<br><ul class=\"bb_ul\"><li>Choice of  2 Elite Players (1 offensive &amp; 1 defensive)<br><\/li><li>All Madden Gear<br><\/li><li>Madden Strategy Item<\/li><\/ul><\/p><br><h1>About the Game<\/h1>Play your way into the history books in Madden NFL 23.<br><br>Control your impact with every decision in all-new ways. Call the shots in Franchise with free agency and trade logic updates, play your way into the history books in Face of the Franchise: The League, and assemble the most powerful roster in all of Madden Ultimate Team™.<br><br><strong>Face of the Franchise: The League<\/strong><br>The League drops you into your fifth NFL season at a skill position of your choice (QB, WR, RB, CB, MLB), and you’re seeking a fresh start with a new team. Negotiate a 1-year “prove-it” contract with one of 32 NFL teams, and show out with great on-field performance to earn rewards and level up. The addition of New Drive Goals and Drive Summaries allows you to tweak your experience throughout a game and get feedback and rewards based on how well you play. Get performance boosts from weekly activities and training between games while Madden Ratings Adjustor Chad Johnson guides your career development by providing ratings updates as you strive for the highest level of prestige on your Road to 99. Will your NFL career rank among the all-time greats? It’s up to you.<br><br><strong>Franchise<\/strong><br>Plan and strategize like an NFL head coach with refined scouting, staff management, and weekly strategy features to take your Franchise to the top. New athlete motivations like team location and salary demands factor into contract negotiations and add to the drama of NFL free agency within Franchise. Updated Trade Logic AI represents the value of star players more accurately for fair and more realistic offers.<br><br><strong>Madden Ultimate Team<\/strong><br>Develop your dream fantasy roster of current NFL superstars, Hall of Fame legends, and more. Always have something to play for with the first-ever Field Pass challenge and reward tracker in Madden Ultimate Team. Play to earn MUT Champions entry tokens and choose to compete at your convenience. Simplified Set building lets you navigate your content binder more effectively so you can focus on improving your Ultimate Team roster all season.<br><br>This game includes optional in-game purchases of virtual currency that can be used to acquire virtual in-game items, including a random selection of virtual in-game items.","about_the_game":"Play your way into the history books in Madden NFL 23.<br><br>Control your impact with every decision in all-new ways. Call the shots in Franchise with free agency and trade logic updates, play your way into the history books in Face of the Franchise: The League, and assemble the most powerful roster in all of Madden Ultimate Team™.<br><br><strong>Face of the Franchise: The League<\/strong><br>The League drops you into your fifth NFL season at a skill position of your choice (QB, WR, RB, CB, MLB), and you’re seeking a fresh start with a new team. Negotiate a 1-year “prove-it” contract with one of 32 NFL teams, and show out with great on-field performance to earn rewards and level up. The addition of New Drive Goals and Drive Summaries allows you to tweak your experience throughout a game and get feedback and rewards based on how well you play. Get performance boosts from weekly activities and training between games while Madden Ratings Adjustor Chad Johnson guides your career development by providing ratings updates as you strive for the highest level of prestige on your Road to 99. Will your NFL career rank among the all-time greats? It’s up to you.<br><br><strong>Franchise<\/strong><br>Plan and strategize like an NFL head coach with refined scouting, staff management, and weekly strategy features to take your Franchise to the top. New athlete motivations like team location and salary demands factor into contract negotiations and add to the drama of NFL free agency within Franchise. Updated Trade Logic AI represents the value of star players more accurately for fair and more realistic offers.<br><br><strong>Madden Ultimate Team<\/strong><br>Develop your dream fantasy roster of current NFL superstars, Hall of Fame legends, and more. Always have something to play for with the first-ever Field Pass challenge and reward tracker in Madden Ultimate Team. Play to earn MUT Champions entry tokens and choose to compete at your convenience. Simplified Set building lets you navigate your content binder more effectively so you can focus on improving your Ultimate Team roster all season.<br><br>This game includes optional in-game purchases of virtual currency that can be used to acquire virtual in-game items, including a random selection of virtual in-game items.","short_description":"Play your way into the history books. Control your impact with every decision in all-new ways. Call the shots in Franchise with free agency and trade logic updates, leave a legacy in Face of the Franchise: The League, and assemble the most powerful roster in all of Madden Ultimate Team™.","supported_languages":"English<strong>*<\/strong><br><strong>*<\/strong>languages with full audio support","header_image":"https:\/\/cdn.akamai.steamstatic.com\/steam\/apps\/1760250\/header.jpg?t=1658764963","website":"https:\/\/www.ea.com\/games\/madden-nfl\/madden-nfl-23","pc_requirements":{"minimum":"<strong>Minimum:<\/strong><br><ul class=\"bb_ul\"><li><strong>OS:<\/strong> Windows 10<br><\/li><li><strong>Processor:<\/strong> Athlon X4 880K @4GHz or better, Core i3-6100 @3.7GHz or better<br><\/li><li><strong>Memory:<\/strong> 8 GB RAM<br><\/li><li><strong>Graphics:<\/strong> Radeon RX 460 or Equivalent, GeForce GTX 660 Equivalent<br><\/li><li><strong>DirectX:<\/strong> Version 11<br><\/li><li><strong>Network:<\/strong> Broadband Internet connection<br><\/li><li><strong>Storage:<\/strong> 50 GB available space<br><\/li><li><strong>Additional Notes:<\/strong> 512 KBPS or Faster Internet Connection<\/li><\/ul>","recommended":"<strong>Recommended:<\/strong><br><ul class=\"bb_ul\"><li><strong>OS:<\/strong> Windows 10<br><\/li><li><strong>Processor:<\/strong> FX 8150 @3.6GHz or better, Core i5-3350 @3.40GHz or better<br><\/li><li><strong>Memory:<\/strong> 12 GB RAM<br><\/li><li><strong>Graphics:<\/strong> Radeon R9 270x or Equivalent, GeForce GTX 680 or Equivalent<br><\/li><li><strong>DirectX:<\/strong> Version 11<br><\/li><li><strong>Network:<\/strong> Broadband Internet connection<br><\/li><li><strong>Storage:<\/strong> 50 GB available space<br><\/li><li><strong>Additional Notes:<\/strong> Broadband Connection<\/li><\/ul>"},"mac_requirements":[],"linux_requirements":[],"legal_notice":"Internet connection; EA account; Steam account; acceptance of EA User Agreement (terms.ea.com); and download & installation of EA’s client software (origin.com\/download) required to play. EA’s Privacy & Cookie Policy applies to your use of EA’s services. You must link your EA and Steam accounts to play; EA will share your account id and individual game and play records with Steam to validate your purchase and\/or refund request. Access to software content is limited to one EA & one Steam account & is non-transferable after purchase. You may need to be 13+ or 16+ to register for an EA account (age may vary, see http:\/\/o.ea.com\/ea\/child-access for details). Some content may require gameplay to unlock. Content updates may be downloaded automatically, require additional storage, and incur bandwidth usage fees. EA may provide certain free incremental content &\/or updates. EA may retire online features after 30 days notice posted on ea.com\/service-updates. Madden Points and All Madden Edition not available in Belgium.<br \/>\r\n<br \/>\r\nEA User Agreement: terms.ea.com\/de for German residents and terms.ea.com for all other residents<br \/>\r\nEA Privacy & Cookie Policy: privacy.ea.com\/de for German residents and privacy.ea.com for all other residents","drm_notice":"EA on-line activation and Origin client software installation and background use required.","ext_user_account_notice":"EA Account ","developers":["Tiburon"],"publishers":["Electronic Arts"],"price_overview":{"currency":"UAH","initial":149900,"final":149900,"discount_percent":0,"initial_formatted":"","final_formatted":"1 499₴"},"packages":[689602,689606],"package_groups":[{"name":"default","title":"Buy Madden NFL 23","description":"","selection_text":"Select a purchase option","save_text":"","display_type":0,"is_recurring_subscription":"false","subs":[{"packageid":689602,"percent_savings_text":" ","percent_savings":0,"option_text":"Madden NFL 23 – Standard Edition - 1 499₴","option_description":"","can_get_free_license":"0","is_free_license":false,"price_in_cents_with_discount":149900},{"packageid":689606,"percent_savings_text":" ","percent_savings":0,"option_text":"Madden NFL 23 – Deluxe Edition - 2 499₴","option_description":"","can_get_free_license":"0","is_free_license":false,"price_in_cents_with_discount":249900}]}],"platforms":{"windows":true,"mac":false,"linux":false},"categories":[{"id":2,"description":"Single-player"},{"id":1,"description":"Multi-player"},{"id":49,"description":"PvP"},{"id":36,"description":"Online PvP"},{"id":9,"description":"Co-op"},{"id":39,"description":"Shared\/Split Screen Co-op"},{"id":24,"description":"Shared\/Split Screen"},{"id":22,"description":"Steam Achievements"},{"id":28,"description":"Full controller support"},{"id":35,"description":"In-App Purchases"},{"id":44,"description":"Remote Play Together"}],"genres":[{"id":"28","description":"Simulation"},{"id":"18","description":"Sports"}],"screenshots":[{"id":0,"path_thumbnail":"https:\/\/cdn.akamai.steamstatic.com\/steam\/apps\/1760250\/ss_2942d299e617a185f31962732ebe6785f2fdae26.600x338.jpg?t=1658764963","path_full":"https:\/\/cdn.akamai.steamstatic.com\/steam\/apps\/1760250\/ss_2942d299e617a185f31962732ebe6785f2fdae26.1920x1080.jpg?t=1658764963"},{"id":1,"path_thumbnail":"https:\/\/cdn.akamai.steamstatic.com\/steam\/apps\/1760250\/ss_42743736a2e27ade660c2d08c17955f2a131be52.600x338.jpg?t=1658764963","path_full":"https:\/\/cdn.akamai.steamstatic.com\/steam\/apps\/1760250\/ss_42743736a2e27ade660c2d08c17955f2a131be52.1920x1080.jpg?t=1658764963"},{"id":2,"path_thumbnail":"https:\/\/cdn.akamai.steamstatic.com\/steam\/apps\/1760250\/ss_e7658dc3c3041e528cf8a5d19819e0966e9ff923.600x338.jpg?t=1658764963","path_full":"https:\/\/cdn.akamai.steamstatic.com\/steam\/apps\/1760250\/ss_e7658dc3c3041e528cf8a5d19819e0966e9ff923.1920x1080.jpg?t=1658764963"},{"id":3,"path_thumbnail":"https:\/\/cdn.akamai.steamstatic.com\/steam\/apps\/1760250\/ss_79ebc88e14ec32f74278a1e7a864c80aa7d53248.600x338.jpg?t=1658764963","path_full":"https:\/\/cdn.akamai.steamstatic.com\/steam\/apps\/1760250\/ss_79ebc88e14ec32f74278a1e7a864c80aa7d53248.1920x1080.jpg?t=1658764963"},{"id":4,"path_thumbnail":"https:\/\/cdn.akamai.steamstatic.com\/steam\/apps\/1760250\/ss_2c96ecf0eee060a41e6997e0f20a9b9eda00f292.600x338.jpg?t=1658764963","path_full":"https:\/\/cdn.akamai.steamstatic.com\/steam\/apps\/1760250\/ss_2c96ecf0eee060a41e6997e0f20a9b9eda00f292.1920x1080.jpg?t=1658764963"}],"movies":[{"id":256898034,"name":"GEN4 Trailer 23","thumbnail":"https:\/\/cdn.akamai.steamstatic.com\/steam\/apps\/256898034\/movie.293x165.jpg?t=1658764956","webm":{"480":"http:\/\/cdn.akamai.steamstatic.com\/steam\/apps\/256898034\/movie480_vp9.webm?t=1658764956","max":"http:\/\/cdn.akamai.steamstatic.com\/steam\/apps\/256898034\/movie_max_vp9.webm?t=1658764956"},"mp4":{"480":"http:\/\/cdn.akamai.steamstatic.com\/steam\/apps\/256898034\/movie480.mp4?t=1658764956","max":"http:\/\/cdn.akamai.steamstatic.com\/steam\/apps\/256898034\/movie_max.mp4?t=1658764956"},"highlight":true}],"release_date":{"coming_soon":true,"date":"19 Aug, 2022"},"support_info":{"url":"https:\/\/help.ea.com\/","email":""},"background":"https:\/\/cdn.akamai.steamstatic.com\/steam\/apps\/1760250\/page_bg_generated_v6b.jpg?t=1658764963","background_raw":"https:\/\/cdn.akamai.steamstatic.com\/steam\/apps\/1760250\/page_bg_generated.jpg?t=1658764963","content_descriptors":{"ids":[],"notes":null}}}}