{"1556560":{"success":true,"data":{"type":"game","name":"Death Tale Pandora's Box","steam_appid":1556560,"required_age":0,"is_free":false,"detailed_description":"In This game assume control of Messorem aka. Death, and go deep in the Pandora Box to restore the order or maybe Create more CHAOS<br \/>\r\nFight with a GIANT ARSENAL of randomly genereted guns in random rooms, IN THIS FAST ACTION ROGUELIKE, in each run, Fight thousands of MONSTERS and  BOSSES<br \/>\r\nand face your destiny in the last Room.<br \/>\r\n<br \/>\r\n<br \/>\r\nFound Skins,LOOT,Items, Enchants, and much much MORE","about_the_game":"In This game assume control of Messorem aka. Death, and go deep in the Pandora Box to restore the order or maybe Create more CHAOS<br \/>\r\nFight with a GIANT ARSENAL of randomly genereted guns in random rooms, IN THIS FAST ACTION ROGUELIKE, in each run, Fight thousands of MONSTERS and  BOSSES<br \/>\r\nand face your destiny in the last Room.<br \/>\r\n<br \/>\r\n<br \/>\r\nFound Skins,LOOT,Items, Enchants, and much much MORE","short_description":"In this action roguelike you will found a almost infinite arnesal of randomly procedural genereted weapons, with giant bosses, bullets and death, you are in the pandoras box its your choice what will you do peace or chaos?","supported_languages":"English<strong>*<\/strong>, Portuguese - Brazil<br><strong>*<\/strong>languages with full audio support","header_image":"https:\/\/cdn.akamai.steamstatic.com\/steam\/apps\/1556560\/header.jpg?t=1657040034","website":null,"pc_requirements":{"minimum":"<strong>Minimum:<\/strong><br><ul class=\"bb_ul\"><li><strong>OS:<\/strong> Windows 7<br><\/li><li><strong>Processor:<\/strong> Icore 3 2Th gen<br><\/li><li><strong>Memory:<\/strong> 2 GB RAM<br><\/li><li><strong>Graphics:<\/strong> GeForce 7600 GS (512 MB) or equivalent<br><\/li><li><strong>DirectX:<\/strong> Version 7.1<br><\/li><li><strong>Storage:<\/strong> 1 GB available space<\/li><\/ul>","recommended":"<strong>Recommended:<\/strong><br><ul class=\"bb_ul\"><li><strong>OS:<\/strong> Windows 7 or higher<br><\/li><li><strong>Processor:<\/strong> Icore 3 5Th gen<br><\/li><li><strong>Graphics:<\/strong> GeForce GTX 660<br><\/li><li><strong>Storage:<\/strong> 1 GB available space<\/li><\/ul>"},"mac_requirements":[],"linux_requirements":[],"legal_notice":"\"Todos os Direitos Reservados A Nyx Works©\"<br \/>\r\n\"All Rights Belong To  Nyx Works©\"","developers":["Nyx Works"],"publishers":["Nyx Works"],"package_groups":[],"platforms":{"windows":true,"mac":false,"linux":false},"categories":[{"id":2,"description":"Single-player"},{"id":22,"description":"Steam Achievements"}],"genres":[{"id":"1","description":"Action"},{"id":"23","description":"Indie"}],"screenshots":[{"id":0,"path_thumbnail":"https:\/\/cdn.akamai.steamstatic.com\/steam\/apps\/1556560\/ss_574d792eb2cc6490aa30dc76552513965b641530.600x338.jpg?t=1657040034","path_full":"https:\/\/cdn.akamai.steamstatic.com\/steam\/apps\/1556560\/ss_574d792eb2cc6490aa30dc76552513965b641530.1920x1080.jpg?t=1657040034"},{"id":1,"path_thumbnail":"https:\/\/cdn.akamai.steamstatic.com\/steam\/apps\/1556560\/ss_ddd1e1c2c42939b4ed874b2f040f5b809d4782a9.600x338.jpg?t=1657040034","path_full":"https:\/\/cdn.akamai.steamstatic.com\/steam\/apps\/1556560\/ss_ddd1e1c2c42939b4ed874b2f040f5b809d4782a9.1920x1080.jpg?t=1657040034"},{"id":2,"path_thumbnail":"https:\/\/cdn.akamai.steamstatic.com\/steam\/apps\/1556560\/ss_44d430e50a8500d1fb0e6a7a4b0f0bb07402632d.600x338.jpg?t=1657040034","path_full":"https:\/\/cdn.akamai.steamstatic.com\/steam\/apps\/1556560\/ss_44d430e50a8500d1fb0e6a7a4b0f0bb07402632d.1920x1080.jpg?t=1657040034"},{"id":3,"path_thumbnail":"https:\/\/cdn.akamai.steamstatic.com\/steam\/apps\/1556560\/ss_308ce09fca74e09d74357bc6c0c914702d2e0420.600x338.jpg?t=1657040034","path_full":"https:\/\/cdn.akamai.steamstatic.com\/steam\/apps\/1556560\/ss_308ce09fca74e09d74357bc6c0c914702d2e0420.1920x1080.jpg?t=1657040034"},{"id":4,"path_thumbnail":"https:\/\/cdn.akamai.steamstatic.com\/steam\/apps\/1556560\/ss_7011ba828932f95b73b8ce00e87a688aa9721a5a.600x338.jpg?t=1657040034","path_full":"https:\/\/cdn.akamai.steamstatic.com\/steam\/apps\/1556560\/ss_7011ba828932f95b73b8ce00e87a688aa9721a5a.1920x1080.jpg?t=1657040034"},{"id":5,"path_thumbnail":"https:\/\/cdn.akamai.steamstatic.com\/steam\/apps\/1556560\/ss_3b71e4c5d614b00848b0403ddd7bae1646552029.600x338.jpg?t=1657040034","path_full":"https:\/\/cdn.akamai.steamstatic.com\/steam\/apps\/1556560\/ss_3b71e4c5d614b00848b0403ddd7bae1646552029.1920x1080.jpg?t=1657040034"},{"id":6,"path_thumbnail":"https:\/\/cdn.akamai.steamstatic.com\/steam\/apps\/1556560\/ss_446c89b3906c56c2041eea513b06f424125ff90d.600x338.jpg?t=1657040034","path_full":"https:\/\/cdn.akamai.steamstatic.com\/steam\/apps\/1556560\/ss_446c89b3906c56c2041eea513b06f424125ff90d.1920x1080.jpg?t=1657040034"},{"id":7,"path_thumbnail":"https:\/\/cdn.akamai.steamstatic.com\/steam\/apps\/1556560\/ss_adb0ea13532431527701a6865de681a422fd2681.600x338.jpg?t=1657040034","path_full":"https:\/\/cdn.akamai.steamstatic.com\/steam\/apps\/1556560\/ss_adb0ea13532431527701a6865de681a422fd2681.1920x1080.jpg?t=1657040034"},{"id":8,"path_thumbnail":"https:\/\/cdn.akamai.steamstatic.com\/steam\/apps\/1556560\/ss_74d94fd0f6ca44fb65dccb027a630c288a220b26.600x338.jpg?t=1657040034","path_full":"https:\/\/cdn.akamai.steamstatic.com\/steam\/apps\/1556560\/ss_74d94fd0f6ca44fb65dccb027a630c288a220b26.1920x1080.jpg?t=1657040034"}],"movies":[{"id":256822775,"name":"DEATH TALE TEASER","thumbnail":"https:\/\/cdn.akamai.steamstatic.com\/steam\/apps\/256822775\/movie.293x165.jpg?t=1618753144","webm":{"480":"http:\/\/cdn.akamai.steamstatic.com\/steam\/apps\/256822775\/movie480_vp9.webm?t=1618753144","max":"http:\/\/cdn.akamai.steamstatic.com\/steam\/apps\/256822775\/movie_max_vp9.webm?t=1618753144"},"mp4":{"480":"http:\/\/cdn.akamai.steamstatic.com\/steam\/apps\/256822775\/movie480.mp4?t=1618753144","max":"http:\/\/cdn.akamai.steamstatic.com\/steam\/apps\/256822775\/movie_max.mp4?t=1618753144"},"highlight":true}],"release_date":{"coming_soon":true,"date":"In The Right Time"},"support_info":{"url":"","email":"nyxkauan@gmail.com"},"background":"https:\/\/cdn.akamai.steamstatic.com\/steam\/apps\/1556560\/page_bg_generated_v6b.jpg?t=1657040034","background_raw":"https:\/\/cdn.akamai.steamstatic.com\/steam\/apps\/1556560\/page.bg.jpg?t=1657040034","content_descriptors":{"ids":[],"notes":null}}}}