{"1824810":{"success":true,"data":{"type":"game","name":"VR New York Story, Settle in New York","steam_appid":1824810,"required_age":0,"is_free":false,"detailed_description":"VR New York Story's second edition, &quot;Settle in New York&quot; is now released!<br \/>\r\nConsisting of 120 episodes including various situations, this is a total package for you to advance your English speaking skills!<br \/>\r\n<br \/>\r\n<br \/>\r\nAre you hesitating to go study abroad because you have a tight budget?<br \/>\r\n→Experience studying in New York virtually for a cheaper price! You will learn how to speak 3800 different expressions in English as well as enjoying on-the-spot experiences in 50 different locations in New York.<br \/>\r\n<br \/>\r\nAre you still hanging out with friends who speak the same language, while studying overseas?<br \/>\r\n→Communicate with 32 different foreign 3D characters like Sam and Barbara and become real friends!<br \/>\r\n<br \/>\r\nAre you too nervous to speak when you bump into foreigners, worrying that you will make a mistake?<br \/>\r\n→Don’t be afraid! Practice and enjoy daily life conversations with various characters and gain confidence!<br \/>\r\n<br \/>\r\nAre you stuck at home wanting to travel to New York?<br \/>\r\n→You only need a VR headset and once you make a one-time purchase of &quot;VR New York Story, Settle in New York&quot;, we're all set. Off to New York!<br \/>\r\n<br \/>\r\nAre you looking for jobs abroad but worried about what to say during your interview or in real life business situations?<br \/>\r\n→VR New York Story, Settle in New York will get you ready for all sorts of circumstances that could happen when you live abroad, through 120 episodes.<br \/>\r\n<br \/>\r\n<br \/>\r\nMain Episodes<br \/>\r\n<br \/>\r\n⊙Going through job interviews for a part-time job<br \/>\r\n⊙Getting a salary raise offer<br \/>\r\n⊙Going to the dentist<br \/>\r\n⊙Renting a car for vacation<br \/>\r\n⊙Working part-time at a fashion store<br \/>\r\n⊙Getting a loan counseling from the bank<br \/>\r\n⊙Restoring a relationship with your x-boyfriend<br \/>\r\n<br \/>\r\nDive right into VR New York Story, Settle in New York to check-out more episodes including traveling, daily life, life at work, having a relationship and more!<br \/>\r\n<br \/>\r\n<br \/>\r\nKey Features<br \/>\r\n<br \/>\r\n⊙Communicate with 32 different 3D characters using &quot;Voice Recognition&quot; technology!<br \/>\r\n⊙Feel as if you were in New York with an artificially built, but a realistic-looking environment based on &quot;high quality VR technology&quot;!<br \/>\r\n⊙Interact actively with characters through an Emotion meter that shows you how the characters feel about this conversation!<br \/>\r\n⊙Check for correct pronunciation, intonation, grammar, and fluency in total through our evaluation system!<br \/>\r\n⊙Learn background knowledge as well as English speaking with this well-organized challenge system!","about_the_game":"VR New York Story's second edition, &quot;Settle in New York&quot; is now released!<br \/>\r\nConsisting of 120 episodes including various situations, this is a total package for you to advance your English speaking skills!<br \/>\r\n<br \/>\r\n<br \/>\r\nAre you hesitating to go study abroad because you have a tight budget?<br \/>\r\n→Experience studying in New York virtually for a cheaper price! You will learn how to speak 3800 different expressions in English as well as enjoying on-the-spot experiences in 50 different locations in New York.<br \/>\r\n<br \/>\r\nAre you still hanging out with friends who speak the same language, while studying overseas?<br \/>\r\n→Communicate with 32 different foreign 3D characters like Sam and Barbara and become real friends!<br \/>\r\n<br \/>\r\nAre you too nervous to speak when you bump into foreigners, worrying that you will make a mistake?<br \/>\r\n→Don’t be afraid! Practice and enjoy daily life conversations with various characters and gain confidence!<br \/>\r\n<br \/>\r\nAre you stuck at home wanting to travel to New York?<br \/>\r\n→You only need a VR headset and once you make a one-time purchase of &quot;VR New York Story, Settle in New York&quot;, we're all set. Off to New York!<br \/>\r\n<br \/>\r\nAre you looking for jobs abroad but worried about what to say during your interview or in real life business situations?<br \/>\r\n→VR New York Story, Settle in New York will get you ready for all sorts of circumstances that could happen when you live abroad, through 120 episodes.<br \/>\r\n<br \/>\r\n<br \/>\r\nMain Episodes<br \/>\r\n<br \/>\r\n⊙Going through job interviews for a part-time job<br \/>\r\n⊙Getting a salary raise offer<br \/>\r\n⊙Going to the dentist<br \/>\r\n⊙Renting a car for vacation<br \/>\r\n⊙Working part-time at a fashion store<br \/>\r\n⊙Getting a loan counseling from the bank<br \/>\r\n⊙Restoring a relationship with your x-boyfriend<br \/>\r\n<br \/>\r\nDive right into VR New York Story, Settle in New York to check-out more episodes including traveling, daily life, life at work, having a relationship and more!<br \/>\r\n<br \/>\r\n<br \/>\r\nKey Features<br \/>\r\n<br \/>\r\n⊙Communicate with 32 different 3D characters using &quot;Voice Recognition&quot; technology!<br \/>\r\n⊙Feel as if you were in New York with an artificially built, but a realistic-looking environment based on &quot;high quality VR technology&quot;!<br \/>\r\n⊙Interact actively with characters through an Emotion meter that shows you how the characters feel about this conversation!<br \/>\r\n⊙Check for correct pronunciation, intonation, grammar, and fluency in total through our evaluation system!<br \/>\r\n⊙Learn background knowledge as well as English speaking with this well-organized challenge system!","short_description":"VR New York Story's second edition, &quot;Settle in New York&quot; is now finally released! Consisting of 120 episodes including various situations, this is a total package for you to advance your English speaking skills! With Virtual Reality technology, you will feel as if you are in New York!","supported_languages":"Korean, Simplified Chinese","header_image":"https:\/\/cdn.akamai.steamstatic.com\/steam\/apps\/1824810\/header.jpg?t=1640675700","website":null,"pc_requirements":{"minimum":"<strong>Minimum:<\/strong><br><ul class=\"bb_ul\"><li><strong>OS:<\/strong> Windows 7 Service Pack 1 (SP1)<br><\/li><li><strong>Processor:<\/strong> Intel i5-4590 or AMD FX 8350<br><\/li><li><strong>Memory:<\/strong> 8 GB RAM<br><\/li><li><strong>Graphics:<\/strong> Nvidia GeForce GTX 970 or AMD Radeon R9 290 equivalent<br><\/li><li><strong>DirectX:<\/strong> Version 11<br><\/li><li><strong>Storage:<\/strong> 3 GB available space<\/li><\/ul>","recommended":"<strong>Recommended:<\/strong><br><ul class=\"bb_ul\"><li><strong>OS:<\/strong> Windows 10<br><\/li><li><strong>Processor:<\/strong> Intel i5-4590 or AMD FX 8350<br><\/li><li><strong>Memory:<\/strong> 16 GB RAM<br><\/li><li><strong>Graphics:<\/strong> Nvidia GeForce GTX 1060 or AMD Radeon RX 480 equivalent or better<br><\/li><li><strong>DirectX:<\/strong> Version 11<br><\/li><li><strong>Storage:<\/strong> 3 GB available space<\/li><\/ul>"},"mac_requirements":[],"linux_requirements":[],"developers":["Aiitone Co.,Ltd"],"publishers":["Aiitone Co.,Ltd"],"price_overview":{"currency":"UAH","initial":16900,"final":16900,"discount_percent":0,"initial_formatted":"","final_formatted":"169₴"},"packages":[656211],"package_groups":[{"name":"default","title":"Buy VR New York Story, Settle in New York","description":"","selection_text":"Select a purchase option","save_text":"","display_type":0,"is_recurring_subscription":"false","subs":[{"packageid":656211,"percent_savings_text":" ","percent_savings":0,"option_text":"VR New York Story, Settle in New York - 169₴","option_description":"","can_get_free_license":"0","is_free_license":false,"price_in_cents_with_discount":16900}]}],"platforms":{"windows":true,"mac":false,"linux":false},"categories":[{"id":2,"description":"Single-player"}],"genres":[{"id":"25","description":"Adventure"},{"id":"4","description":"Casual"},{"id":"23","description":"Indie"},{"id":"28","description":"Simulation"}],"screenshots":[{"id":0,"path_thumbnail":"https:\/\/cdn.akamai.steamstatic.com\/steam\/apps\/1824810\/ss_1c3a3adec5aa96382c00eaceed1faa6c07a7b4e8.600x338.jpg?t=1640675700","path_full":"https:\/\/cdn.akamai.steamstatic.com\/steam\/apps\/1824810\/ss_1c3a3adec5aa96382c00eaceed1faa6c07a7b4e8.1920x1080.jpg?t=1640675700"},{"id":1,"path_thumbnail":"https:\/\/cdn.akamai.steamstatic.com\/steam\/apps\/1824810\/ss_f101710b60a1b0573c47ef58b226bbfe367acd47.600x338.jpg?t=1640675700","path_full":"https:\/\/cdn.akamai.steamstatic.com\/steam\/apps\/1824810\/ss_f101710b60a1b0573c47ef58b226bbfe367acd47.1920x1080.jpg?t=1640675700"},{"id":2,"path_thumbnail":"https:\/\/cdn.akamai.steamstatic.com\/steam\/apps\/1824810\/ss_8cbaad9a1cd0691ff037fcc7a95c62f93a91f05d.600x338.jpg?t=1640675700","path_full":"https:\/\/cdn.akamai.steamstatic.com\/steam\/apps\/1824810\/ss_8cbaad9a1cd0691ff037fcc7a95c62f93a91f05d.1920x1080.jpg?t=1640675700"},{"id":3,"path_thumbnail":"https:\/\/cdn.akamai.steamstatic.com\/steam\/apps\/1824810\/ss_5cc0854e0a93b5079040255bcba8bb3048624935.600x338.jpg?t=1640675700","path_full":"https:\/\/cdn.akamai.steamstatic.com\/steam\/apps\/1824810\/ss_5cc0854e0a93b5079040255bcba8bb3048624935.1920x1080.jpg?t=1640675700"},{"id":4,"path_thumbnail":"https:\/\/cdn.akamai.steamstatic.com\/steam\/apps\/1824810\/ss_a2ece68910badb4c36f64ed0c5715b3493dc9899.600x338.jpg?t=1640675700","path_full":"https:\/\/cdn.akamai.steamstatic.com\/steam\/apps\/1824810\/ss_a2ece68910badb4c36f64ed0c5715b3493dc9899.1920x1080.jpg?t=1640675700"}],"movies":[{"id":256864089,"name":"Settle in New York","thumbnail":"https:\/\/cdn.akamai.steamstatic.com\/steam\/apps\/256864089\/movie.293x165.jpg?t=1639455666","webm":{"480":"http:\/\/cdn.akamai.steamstatic.com\/steam\/apps\/256864089\/movie480_vp9.webm?t=1639455666","max":"http:\/\/cdn.akamai.steamstatic.com\/steam\/apps\/256864089\/movie_max_vp9.webm?t=1639455666"},"mp4":{"480":"http:\/\/cdn.akamai.steamstatic.com\/steam\/apps\/256864089\/movie480.mp4?t=1639455666","max":"http:\/\/cdn.akamai.steamstatic.com\/steam\/apps\/256864089\/movie_max.mp4?t=1639455666"},"highlight":true}],"release_date":{"coming_soon":false,"date":"27 Dec, 2021"},"support_info":{"url":"http:\/\/www.aiitone.com","email":"aiitone_fb@aiitone.com"},"background":"https:\/\/cdn.akamai.steamstatic.com\/steam\/apps\/1824810\/page_bg_generated_v6b.jpg?t=1640675700","background_raw":"https:\/\/cdn.akamai.steamstatic.com\/steam\/apps\/1824810\/page_bg_generated.jpg?t=1640675700","content_descriptors":{"ids":[],"notes":null}}}}