{"1604730":{"success":true,"data":{"type":"game","name":"Probability Race","steam_appid":1604730,"required_age":0,"is_free":false,"controller_support":"full","detailed_description":"Probability Race is a futuristic racing game. You must use logic, math, probability and luck to win the championship. Play a great variety of minigames  and compete in turn based races every day. Unlock abilities and race your way to victory in this platform\/stragegy\/turnbased game.","about_the_game":"Probability Race is a futuristic racing game. You must use logic, math, probability and luck to win the championship. Play a great variety of minigames  and compete in turn based races every day. Unlock abilities and race your way to victory in this platform\/stragegy\/turnbased game.","short_description":"Probability Race is a futuristic racing game. You must use logic, math, probability and luck to win the championship. Play a great variety of minigames and compete in turn based races every day. Unlock abilities and race your way to victory in this platform\/stragegy\/turnbased game.","supported_languages":"English, Danish","header_image":"https:\/\/cdn.akamai.steamstatic.com\/steam\/apps\/1604730\/header.jpg?t=1622375647","website":"http:\/\/amigos500.dk","pc_requirements":{"minimum":"<strong>Minimum:<\/strong><br><ul class=\"bb_ul\"><li><strong>OS:<\/strong> WindowsR 7\/8\/8.1\/10 (32bit\/64bit)<br><\/li><li><strong>Processor:<\/strong> Intel Core 2 Duo or better<br><\/li><li><strong>Memory:<\/strong> 2 GB RAM<br><\/li><li><strong>Graphics:<\/strong> DirectX 9\/OpenGL 4.1 capable GPU<br><\/li><li><strong>DirectX:<\/strong> Version 9.0<br><\/li><li><strong>Storage:<\/strong> 320 MB available space<\/li><\/ul>"},"mac_requirements":{"minimum":"<strong>Minimum:<\/strong><br><ul class=\"bb_ul\"><li><strong>OS:<\/strong> Mac OS X 10.10 or better<br><\/li><li><strong>Processor:<\/strong> Intel Core2 Duo or better<br><\/li><li><strong>Memory:<\/strong> 2 GB RAM<br><\/li><li><strong>Graphics:<\/strong> OpenGL 4.1 capable GPU<br><\/li><li><strong>Storage:<\/strong> 650 MB available space<\/li><\/ul>"},"linux_requirements":[],"developers":["Amigos 500"],"publishers":["Amigos 500"],"demos":[{"appid":1605660,"description":""}],"price_overview":{"currency":"UAH","initial":5900,"final":5900,"discount_percent":0,"initial_formatted":"","final_formatted":"59₴"},"packages":[569030],"package_groups":[{"name":"default","title":"Buy Probability Race","description":"","selection_text":"Select a purchase option","save_text":"","display_type":0,"is_recurring_subscription":"false","subs":[{"packageid":569030,"percent_savings_text":" ","percent_savings":0,"option_text":"Probability Race - 59₴","option_description":"","can_get_free_license":"0","is_free_license":false,"price_in_cents_with_discount":5900}]}],"platforms":{"windows":true,"mac":true,"linux":false},"categories":[{"id":2,"description":"Single-player"},{"id":28,"description":"Full controller support"}],"genres":[{"id":"23","description":"Indie"},{"id":"2","description":"Strategy"}],"screenshots":[{"id":0,"path_thumbnail":"https:\/\/cdn.akamai.steamstatic.com\/steam\/apps\/1604730\/ss_9fdaeb4b88b4105830bc4d124caa7559234f99c0.600x338.jpg?t=1622375647","path_full":"https:\/\/cdn.akamai.steamstatic.com\/steam\/apps\/1604730\/ss_9fdaeb4b88b4105830bc4d124caa7559234f99c0.1920x1080.jpg?t=1622375647"},{"id":1,"path_thumbnail":"https:\/\/cdn.akamai.steamstatic.com\/steam\/apps\/1604730\/ss_f7e3e97bfbf9bdac9f66a23410f47aee05a84f42.600x338.jpg?t=1622375647","path_full":"https:\/\/cdn.akamai.steamstatic.com\/steam\/apps\/1604730\/ss_f7e3e97bfbf9bdac9f66a23410f47aee05a84f42.1920x1080.jpg?t=1622375647"},{"id":2,"path_thumbnail":"https:\/\/cdn.akamai.steamstatic.com\/steam\/apps\/1604730\/ss_12fb2a7db1aa09c8e54c88befcb69af39b1b56de.600x338.jpg?t=1622375647","path_full":"https:\/\/cdn.akamai.steamstatic.com\/steam\/apps\/1604730\/ss_12fb2a7db1aa09c8e54c88befcb69af39b1b56de.1920x1080.jpg?t=1622375647"},{"id":3,"path_thumbnail":"https:\/\/cdn.akamai.steamstatic.com\/steam\/apps\/1604730\/ss_d9ed4eb9699d6da73872b360e1e2ad85ad7e4feb.600x338.jpg?t=1622375647","path_full":"https:\/\/cdn.akamai.steamstatic.com\/steam\/apps\/1604730\/ss_d9ed4eb9699d6da73872b360e1e2ad85ad7e4feb.1920x1080.jpg?t=1622375647"},{"id":4,"path_thumbnail":"https:\/\/cdn.akamai.steamstatic.com\/steam\/apps\/1604730\/ss_f2f18721c8010492dd2828607a20f9b764a77c57.600x338.jpg?t=1622375647","path_full":"https:\/\/cdn.akamai.steamstatic.com\/steam\/apps\/1604730\/ss_f2f18721c8010492dd2828607a20f9b764a77c57.1920x1080.jpg?t=1622375647"}],"movies":[{"id":256829996,"name":"Probability Race Trailer","thumbnail":"https:\/\/cdn.akamai.steamstatic.com\/steam\/apps\/256829996\/movie.293x165.jpg?t=1619999018","webm":{"480":"http:\/\/cdn.akamai.steamstatic.com\/steam\/apps\/256829996\/movie480_vp9.webm?t=1619999018","max":"http:\/\/cdn.akamai.steamstatic.com\/steam\/apps\/256829996\/movie_max_vp9.webm?t=1619999018"},"mp4":{"480":"http:\/\/cdn.akamai.steamstatic.com\/steam\/apps\/256829996\/movie480.mp4?t=1619999018","max":"http:\/\/cdn.akamai.steamstatic.com\/steam\/apps\/256829996\/movie_max.mp4?t=1619999018"},"highlight":true}],"release_date":{"coming_soon":false,"date":"28 May, 2021"},"support_info":{"url":"http:\/\/amigos500.dk","email":""},"background":"https:\/\/cdn.akamai.steamstatic.com\/steam\/apps\/1604730\/page_bg_generated_v6b.jpg?t=1622375647","background_raw":"https:\/\/cdn.akamai.steamstatic.com\/steam\/apps\/1604730\/page_bg_generated.jpg?t=1622375647","content_descriptors":{"ids":[],"notes":null}}}}