{"2027460":{"success":true,"data":{"type":"demo","name":"Spellers Demo","steam_appid":2027460,"required_age":0,"is_free":true,"detailed_description":"","about_the_game":"","short_description":"","fullgame":{"appid":"1933010","name":"Spellers"},"supported_languages":"English","header_image":"https:\/\/cdn.akamai.steamstatic.com\/steam\/apps\/2027460\/header.jpg?t=1654550501","website":"https:\/\/yuzugames.com\/","pc_requirements":{"minimum":"<strong>Minimum:<\/strong><br><ul class=\"bb_ul\"><li><strong>OS:<\/strong> Windows 7<br><\/li><li><strong>Processor:<\/strong> 2nd Generation Core i3, AMD A6, or higher<br><\/li><li><strong>Memory:<\/strong> 4 GB RAM<br><\/li><li><strong>Graphics:<\/strong> Nvidia 8800 GT, AMD 5670, Intel HD 3000<br><\/li><li><strong>Storage:<\/strong> 2 GB available space<\/li><\/ul>"},"mac_requirements":[],"linux_requirements":[],"developers":["YuzuGames"],"publishers":["YuzuGames"],"package_groups":[],"platforms":{"windows":true,"mac":false,"linux":false},"categories":[{"id":2,"description":"Single-player"},{"id":1,"description":"Multi-player"},{"id":49,"description":"PvP"},{"id":36,"description":"Online PvP"},{"id":37,"description":"Shared\/Split Screen PvP"},{"id":24,"description":"Shared\/Split Screen"},{"id":10,"description":"Game demo"},{"id":18,"description":"Partial Controller Support"}],"release_date":{"coming_soon":true,"date":"10 Jun, 2022"},"support_info":{"url":"","email":"support@yuzugames.com"},"background":"","background_raw":"","content_descriptors":{"ids":[],"notes":null}}}}