{"1702490":{"success":true,"data":{"type":"game","name":"少女刑侦部","steam_appid":1702490,"required_age":0,"is_free":false,"detailed_description":"<strong>还在等什么？快来和美少女一起破案吧！<\/strong><br><br>游戏中你将被分入一个名为少女刑侦部的组织，在这里你将不断突破自己的极限，挑战一个个扑朔迷离的案件，同时邂逅美女同事，绞尽脑汁和大家一起抓住犯罪凶手。休息时间，你还可以和各位同事改善关系、增进感情、了解大家背后的故事。<br><br><img src=\"https:\/\/cdn.akamai.steamstatic.com\/steam\/apps\/1702490\/extras\/介绍1.png?t=1627183461\" \/><br><br><img src=\"https:\/\/cdn.akamai.steamstatic.com\/steam\/apps\/1702490\/extras\/介绍2.png?t=1627183461\" \/><br><br><img src=\"https:\/\/cdn.akamai.steamstatic.com\/steam\/apps\/1702490\/extras\/介绍3.png?t=1627183461\" \/><br><br><img src=\"https:\/\/cdn.akamai.steamstatic.com\/steam\/apps\/1702490\/extras\/介绍4.png?t=1627183461\" \/><br><br><img src=\"https:\/\/cdn.akamai.steamstatic.com\/steam\/apps\/1702490\/extras\/介绍5.png?t=1627183461\" \/><br><br><img src=\"https:\/\/cdn.akamai.steamstatic.com\/steam\/apps\/1702490\/extras\/介绍6.png?t=1627183461\" \/>","about_the_game":"<strong>还在等什么？快来和美少女一起破案吧！<\/strong><br><br>游戏中你将被分入一个名为少女刑侦部的组织，在这里你将不断突破自己的极限，挑战一个个扑朔迷离的案件，同时邂逅美女同事，绞尽脑汁和大家一起抓住犯罪凶手。休息时间，你还可以和各位同事改善关系、增进感情、了解大家背后的故事。<br><br><img src=\"https:\/\/cdn.akamai.steamstatic.com\/steam\/apps\/1702490\/extras\/介绍1.png?t=1627183461\" \/><br><br><img src=\"https:\/\/cdn.akamai.steamstatic.com\/steam\/apps\/1702490\/extras\/介绍2.png?t=1627183461\" \/><br><br><img src=\"https:\/\/cdn.akamai.steamstatic.com\/steam\/apps\/1702490\/extras\/介绍3.png?t=1627183461\" \/><br><br><img src=\"https:\/\/cdn.akamai.steamstatic.com\/steam\/apps\/1702490\/extras\/介绍4.png?t=1627183461\" \/><br><br><img src=\"https:\/\/cdn.akamai.steamstatic.com\/steam\/apps\/1702490\/extras\/介绍5.png?t=1627183461\" \/><br><br><img src=\"https:\/\/cdn.akamai.steamstatic.com\/steam\/apps\/1702490\/extras\/介绍6.png?t=1627183461\" \/>","short_description":"堂堂男子汉竟然被分配到少女刑侦部？！随着扑朔迷离的案情接踵而至，你需要在各个美少女前展现你的最佳实力！游戏中你将与多个少女一同办案，开动脑筋帮助刑侦部还原事情真相，抓住凶手！于此同时，也请和刑侦部的各位好好相处吧~说不定还会收获意外惊喜？！","supported_languages":"Simplified Chinese, Traditional Chinese","header_image":"https:\/\/cdn.akamai.steamstatic.com\/steam\/apps\/1702490\/header.jpg?t=1627183461","website":null,"pc_requirements":{"minimum":"<strong>Minimum:<\/strong><br><ul class=\"bb_ul\"><li><strong>OS:<\/strong> Windows 7 SP1, Windows 8.1, Windows 10<br><\/li><li><strong>Processor:<\/strong> Intel Core i3 2.00 GHz 或 AMD A10<br><\/li><li><strong>Memory:<\/strong> 2 GB RAM<br><\/li><li><strong>Graphics:<\/strong> Intel® HD Graphics 3000<br><\/li><li><strong>DirectX:<\/strong> Version 11<br><\/li><li><strong>Storage:<\/strong> 10 GB available space<\/li><\/ul>","recommended":"<strong>Recommended:<\/strong><br><ul class=\"bb_ul\"><li><strong>OS:<\/strong> Windows 7 SP1, Windows 8.1, Windows 10<br><\/li><li><strong>Processor:<\/strong> Intel Core i3 2.00 GHz 或 AMD A10<br><\/li><li><strong>Memory:<\/strong> 2 GB RAM<br><\/li><li><strong>Graphics:<\/strong> Intel® HD Graphics 3000<br><\/li><li><strong>DirectX:<\/strong> Version 11<br><\/li><li><strong>Storage:<\/strong> 10 GB available space<\/li><\/ul>"},"mac_requirements":[],"linux_requirements":[],"developers":["Yellow Star Studio"],"publishers":["Yellow Star Studio"],"package_groups":[],"platforms":{"windows":true,"mac":false,"linux":false},"categories":[{"id":2,"description":"Single-player"}],"genres":[{"id":"4","description":"Casual"},{"id":"23","description":"Indie"},{"id":"3","description":"RPG"}],"screenshots":[{"id":0,"path_thumbnail":"https:\/\/cdn.akamai.steamstatic.com\/steam\/apps\/1702490\/ss_a3d4e33b6cbcb0e8e974dcffe8905a50c0568441.600x338.jpg?t=1627183461","path_full":"https:\/\/cdn.akamai.steamstatic.com\/steam\/apps\/1702490\/ss_a3d4e33b6cbcb0e8e974dcffe8905a50c0568441.1920x1080.jpg?t=1627183461"},{"id":1,"path_thumbnail":"https:\/\/cdn.akamai.steamstatic.com\/steam\/apps\/1702490\/ss_91214935ad410bee37327c569e6316223fe78a18.600x338.jpg?t=1627183461","path_full":"https:\/\/cdn.akamai.steamstatic.com\/steam\/apps\/1702490\/ss_91214935ad410bee37327c569e6316223fe78a18.1920x1080.jpg?t=1627183461"},{"id":2,"path_thumbnail":"https:\/\/cdn.akamai.steamstatic.com\/steam\/apps\/1702490\/ss_6fee5c4126145fe66ef03d86be258ffc6388654e.600x338.jpg?t=1627183461","path_full":"https:\/\/cdn.akamai.steamstatic.com\/steam\/apps\/1702490\/ss_6fee5c4126145fe66ef03d86be258ffc6388654e.1920x1080.jpg?t=1627183461"},{"id":3,"path_thumbnail":"https:\/\/cdn.akamai.steamstatic.com\/steam\/apps\/1702490\/ss_caf26630b1e00f9593cd8775e045680524215b6f.600x338.jpg?t=1627183461","path_full":"https:\/\/cdn.akamai.steamstatic.com\/steam\/apps\/1702490\/ss_caf26630b1e00f9593cd8775e045680524215b6f.1920x1080.jpg?t=1627183461"},{"id":4,"path_thumbnail":"https:\/\/cdn.akamai.steamstatic.com\/steam\/apps\/1702490\/ss_212c1f8a1d49d857176da384dbf464b8bec5839c.600x338.jpg?t=1627183461","path_full":"https:\/\/cdn.akamai.steamstatic.com\/steam\/apps\/1702490\/ss_212c1f8a1d49d857176da384dbf464b8bec5839c.1920x1080.jpg?t=1627183461"},{"id":5,"path_thumbnail":"https:\/\/cdn.akamai.steamstatic.com\/steam\/apps\/1702490\/ss_ab53160de0c002636f67e4ba21abd51a283e27a9.600x338.jpg?t=1627183461","path_full":"https:\/\/cdn.akamai.steamstatic.com\/steam\/apps\/1702490\/ss_ab53160de0c002636f67e4ba21abd51a283e27a9.1920x1080.jpg?t=1627183461"},{"id":6,"path_thumbnail":"https:\/\/cdn.akamai.steamstatic.com\/steam\/apps\/1702490\/ss_9306febc0f946e0e8e3dc356d3414faa68cd6cad.600x338.jpg?t=1627183461","path_full":"https:\/\/cdn.akamai.steamstatic.com\/steam\/apps\/1702490\/ss_9306febc0f946e0e8e3dc356d3414faa68cd6cad.1920x1080.jpg?t=1627183461"},{"id":7,"path_thumbnail":"https:\/\/cdn.akamai.steamstatic.com\/steam\/apps\/1702490\/ss_e67b24f2c68b84a096b25bf533df7c7b606ede85.600x338.jpg?t=1627183461","path_full":"https:\/\/cdn.akamai.steamstatic.com\/steam\/apps\/1702490\/ss_e67b24f2c68b84a096b25bf533df7c7b606ede85.1920x1080.jpg?t=1627183461"}],"release_date":{"coming_soon":true,"date":"2021年秋季"},"support_info":{"url":"","email":"349886608@qq.com"},"background":"https:\/\/cdn.akamai.steamstatic.com\/steam\/apps\/1702490\/page_bg_generated_v6b.jpg?t=1627183461","background_raw":"https:\/\/cdn.akamai.steamstatic.com\/steam\/apps\/1702490\/page.bg.jpg?t=1627183461","content_descriptors":{"ids":[1,5],"notes":"此游戏包含的内容可能不适合所有年龄段，或不宜在工作期间访问"}}}}